sal/__init__.py
sal/_modidx.py
sal/arguments.py
sal/cli.py
sal/codegen.py
sal/core.py
sal/frontmatter.py
sal/loaders.py
sal/templates.py
sal/utils.py
sal_code_generator-0.0.35.dist-info/LICENSE
sal_code_generator-0.0.35.dist-info/METADATA
sal_code_generator-0.0.35.dist-info/WHEEL
sal_code_generator-0.0.35.dist-info/entry_points.txt
sal_code_generator-0.0.35.dist-info/top_level.txt
sal_code_generator-0.0.35.dist-info/RECORD
